django_insights/__init__.py
django_insights/apps.py
django_insights/charts.py
django_insights/choices.py
django_insights/database.py
django_insights/managers.py
django_insights/metrics.py
django_insights/metrics_types.py
django_insights/models.py
django_insights/registry.py
django_insights/settings.py
django_insights/urls.py
django_insights/views.py
django_insights/management/__init__.py
django_insights/management/commands/__init__.py
django_insights/management/commands/collect_insights.py
django_insights/migrations/0001_initial.py
django_insights/migrations/__init__.py
django_insights/packages/package.json
django_insights/packages/pnpm-lock.yaml
django_insights/packages/tailwind.config.js
django_insights/packages/src/index.js
django_insights/packages/src/input.css
django_insights/static/insights/css/insights.css
django_insights/static/insights/fonts/ubuntu.ttf
django_insights/static/insights/js/insights.js
django_insights/templates/insights/app.html
django_insights/templates/insights/base.html
django_insights/templates/insights/dashboard.html
django_insights/templatetags/__init__.py
django_insights/templatetags/insight_chart.py
django_insights/templatetags/remove_substr.py
django_insights-0.1.8.dist-info/entry_points.txt
django_insights-0.1.8.dist-info/LICENSE
django_insights-0.1.8.dist-info/WHEEL
django_insights-0.1.8.dist-info/METADATA
django_insights-0.1.8.dist-info/RECORD
