Metadata-Version: 2.1
Name: django-insights
Version: 0.1.8
Summary: Django Insights 
Author-email: DK <dk@terminalkitten.com>
Classifier: Development Status :: 3 - Alpha
Classifier: Environment :: Web Environment
Classifier: Framework :: Django
Classifier: Framework :: Django :: 3.2
Classifier: Framework :: Django :: 4.0
Classifier: Framework :: Django :: 4.1
Classifier: Framework :: Django :: 4.2
Classifier: Framework :: Matplotlib
Classifier: Intended Audience :: Developers
Classifier: Operating System :: OS Independent
Classifier: License :: OSI Approved :: MIT License
Classifier: Programming Language :: Python :: 3 :: Only
Classifier: Programming Language :: Python :: 3.8
Classifier: Programming Language :: Python :: 3.9
Classifier: Programming Language :: Python :: 3.10
Classifier: Programming Language :: Python :: 3.11
Requires-Dist: django
Requires-Dist: matplotlib
Requires-Dist: tqdm
Requires-Dist: black ; extra == "dev"
Requires-Dist: ipython ; extra == "dev"
Requires-Dist: flit ; extra == "dev"
Requires-Dist: flake8 ; extra == "dev"
Requires-Dist: pytest ; extra == "dev"
Requires-Dist: pytest-django ; extra == "dev"
Requires-Dist: mypy ; extra == "dev"
Requires-Dist: isort ; extra == "dev"
Requires-Dist: wheel ; extra == "dev"
Requires-Dist: faker ; extra == "dev"
Requires-Dist: pdoc ; extra == "doc"
Project-URL: Home, https://github.com/terminalkitten/django-insights
Provides-Extra: dev
Provides-Extra: doc
